hisss/__init__.py
hisss/shared.py
hisss/cpp/CMakeLists.txt
hisss/cpp/__init__.py
hisss/cpp/lib.py
hisss/cpp/linux_compile.sh
hisss/cpp/main.cpp
hisss/cpp/windows_compile.bat
hisss/cpp/alglib/alglibinternal.cpp
hisss/cpp/alglib/alglibinternal.h
hisss/cpp/alglib/alglibmisc.cpp
hisss/cpp/alglib/alglibmisc.h
hisss/cpp/alglib/ap.cpp
hisss/cpp/alglib/ap.h
hisss/cpp/alglib/linalg.cpp
hisss/cpp/alglib/linalg.h
hisss/cpp/alglib/linux_compile.sh
hisss/cpp/alglib/optimization.cpp
hisss/cpp/alglib/optimization.h
hisss/cpp/alglib/solvers.cpp
hisss/cpp/alglib/solvers.h
hisss/cpp/alglib/stdafx.h
hisss/cpp/alglib/windows_compile.bat
hisss/cpp/header/battlesnake.h
hisss/cpp/header/battlesnake_helper.h
hisss/cpp/header/nash.h
hisss/cpp/header/utils.h
hisss/cpp/source/battlesnake.cpp
hisss/cpp/source/battlesnake_helper.cpp
hisss/cpp/source/link.cpp
hisss/cpp/source/nash.cpp
hisss/cpp/source/utils.cpp
hisss/equilibria/__init__.py
hisss/equilibria/nash.py
hisss/game/__init__.py
hisss/game/battlesnake.py
hisss/game/config.py
hisss/game/encoding.py
hisss/game/rewards.py
hisss/game/state.py
hisss/game/utils.py
hisss-1.0.0.dist-info/METADATA
hisss-1.0.0.dist-info/WHEEL
hisss-1.0.0.dist-info/RECORD
