Metadata-Version: 2.4
Name: hisss
Version: 1.0.0
Summary: High-Speed Snake Simulator (HISSS)
Author: Robin Schmöcker, Christoph Schnell
Author-email: Yannik Mahlau <mahlau@tnt.uni-hannover.de>
Requires-Python: >=3.12
Requires-Dist: hatchling>=1.28.0
Requires-Dist: numpy>=2.3.5
Requires-Dist: pytest>=9.0.1
